{
  "generatedAt": "2026-04-14T06:31:35.754Z",
  "runId": "24384208494",
  "runNumber": 4,
  "repository": "NXDRAXX/nx-links",
  "actionsUrl": "https://github.com/NXDRAXX/nx-links/actions/runs/24384208494",
  "sources": [
    {
      "key": "steamrip",
      "name": "SteamRip",
      "file": "steamrip.json",
      "updatedThisRun": true,
      "status": "healthy",
      "entries": 1931,
      "dataUpdatedAt": "2026-04-14T06:31:35.830Z"
    },
    {
      "key": "fitgirl",
      "name": "FitGirl",
      "file": "fitgirl.json",
      "updatedThisRun": true,
      "status": "healthy",
      "entries": 6607,
      "dataUpdatedAt": "2026-04-14T06:31:35.871Z"
    },
    {
      "key": "freegog",
      "name": "FreeGOG",
      "file": "freegog.json",
      "updatedThisRun": true,
      "status": "healthy",
      "entries": 5358,
      "dataUpdatedAt": "2026-04-14T06:31:35.885Z"
    },
    {
      "key": "onlinefix",
      "name": "OnlineFix",
      "file": "onlinefix.json",
      "updatedThisRun": true,
      "status": "healthy",
      "entries": 2246,
      "dataUpdatedAt": "2026-04-14T06:31:35.889Z"
    },
    {
      "key": "onlinefix-fixes",
      "name": "OnlineFix Fixes",
      "file": "onlinefix-fixes.json",
      "updatedThisRun": false,
      "status": "failed",
      "entries": 0,
      "dataUpdatedAt": null
    },
    {
      "key": "iggames",
      "name": "IGGames",
      "file": "iggames.json",
      "updatedThisRun": true,
      "status": "healthy",
      "entries": 985,
      "dataUpdatedAt": "2026-04-14T06:31:35.897Z"
    },
    {
      "key": "rexagames",
      "name": "RexaGames",
      "file": "rexagames.json",
      "updatedThisRun": true,
      "status": "healthy",
      "entries": 3025,
      "dataUpdatedAt": "2026-04-14T06:31:35.902Z"
    }
  ],
  "summary": {
    "healthy": 6,
    "stale": 0,
    "failed": 1
  }
}
